Scrapper/PwScrape.py
Scrapper/__init__.py
PowerScrape-0.1.2.dist-info/LICENSE
PowerScrape-0.1.2.dist-info/METADATA
PowerScrape-0.1.2.dist-info/WHEEL
PowerScrape-0.1.2.dist-info/top_level.txt
PowerScrape-0.1.2.dist-info/RECORD
