Metadata-Version: 2.1
Name: PowerScrape
Version: 0.1.2
Summary: A comprehensive and versatile Python module for web scraping.
Home-page: https://github.com/RoseInjector/PowerScrape/
Author: ohioman02
Author-email: gdnunuuwu@gmail.com
Classifier: Programming Language :: Python :: 3
Classifier: License :: OSI Approved :: MIT License
Classifier: Operating System :: OS Independent
License-File: LICENSE
Requires-Dist: requests
Requires-Dist: beautifulsoup4
Requires-Dist: selenium
Requires-Dist: pdfplumber
Requires-Dist: Pillow
Requires-Dist: pytesseract
Requires-Dist: opencv-python
Requires-Dist: numpy
Requires-Dist: cachetools
